flask_spicer/Spice.py
flask_spicer/Spicer.py
flask_spicer/Template.py
flask_spicer/__init__.py
flask_spicer/cli.py
flask_spicer-1.3.0.dist-info/METADATA
flask_spicer-1.3.0.dist-info/WHEEL
flask_spicer-1.3.0.dist-info/entry_points.txt
flask_spicer-1.3.0.dist-info/top_level.txt
flask_spicer-1.3.0.dist-info/RECORD
